<?xml version="1.0" encoding="UTF-8"?>
<!DOCTYPE Publisher
  PUBLIC "-//Springer-Verlag//DTD A++ V2.4//EN" "http://devel.springer.de/A++/V2.4/DTD/A++V2.4.dtd">
<Publisher>
<PublisherInfo>
<PublisherName>Springer-Verlag</PublisherName>
<PublisherLocation>Berlin/Heidelberg</PublisherLocation>
</PublisherInfo>
<Journal>
<JournalInfo JournalProductType="ArchiveJournal" NumberingStyle="Unnumbered">
<JournalID>401</JournalID>
<JournalPrintISSN>0001-6322</JournalPrintISSN>
<JournalElectronicISSN>1432-0533</JournalElectronicISSN>
<JournalTitle>Acta Neuropathologica</JournalTitle>
<JournalAbbreviatedTitle>Acta Neuropathol</JournalAbbreviatedTitle>
      <JournalSubjectGroup>
        <JournalSubject Type="Primary">Medicine &amp; Public Health</JournalSubject>
        <JournalSubject Type="Secondary">Pathology</JournalSubject>
      </JournalSubjectGroup>
</JournalInfo>
<Volume>
<VolumeInfo VolumeType="Regular" TocLevels="0">
<VolumeIDStart>1</VolumeIDStart>
<VolumeIDEnd>1</VolumeIDEnd>
<VolumeIssueCount>5</VolumeIssueCount>
</VolumeInfo>
<Issue IssueType="Regular">
<IssueInfo TocLevels="0">
<IssueIDStart>3</IssueIDStart>
<IssueIDEnd>3</IssueIDEnd>
<IssueArticleCount>8</IssueArticleCount>
<IssueHistory>
<CoverDate>
  <DateString>2. November 1961</DateString>
  <Year>1961</Year>
  <Month>1</Month>
</CoverDate>

</IssueHistory>
<IssueCopyright>
<CopyrightHolderName>Springer-Verlag</CopyrightHolderName>
<CopyrightYear>1961</CopyrightYear>
</IssueCopyright>
</IssueInfo>
<Article ID="Art7">
<ArticleInfo Language="De" ArticleType="BriefCommunication" NumberingStyle="Unnumbered" TocLevels="0" ContainsESM="No">
<ArticleID>BF00687194</ArticleID>
<ArticleDOI>10.1007/BF00687194</ArticleDOI>
<ArticleSequenceNumber>7</ArticleSequenceNumber>
<ArticleTitle Language="De">Histochemische Darstellung der spezifischen Cholinesterase (Azetylcholinesterase) in den nervösen Formationen bei einem Fall von neurogener Appendicopathie mit zentraler Neurombildung</ArticleTitle>
<ArticleCategory>Kurze Originalmitteilungen</ArticleCategory>
<ArticleFirstPage>308</ArticleFirstPage>
<ArticleLastPage>310</ArticleLastPage>
<ArticleHistory>
<RegistrationDate>
<Year>2004</Year>
<Month>11</Month>
<Day>8</Day>
</RegistrationDate>
<Received>
<Year>1961</Year>
<Month>7</Month>
<Day>7</Day>
</Received>
</ArticleHistory>
<ArticleCopyright>
<CopyrightHolderName>Springer-Verlag</CopyrightHolderName>
<CopyrightYear>1961</CopyrightYear>
</ArticleCopyright><ArticleGrants Type="Regular"><MetadataGrant Grant="OpenAccess"/><AbstractGrant Grant="OpenAccess"/><BodyPDFGrant Grant="Restricted"/><BodyHTMLGrant Grant="Restricted"/><BibliographyGrant Grant="Restricted"/><ESMGrant Grant="Restricted"/></ArticleGrants>
<ArticleContext>
<JournalID>401</JournalID>
<VolumeIDStart>1</VolumeIDStart>
<VolumeIDEnd>1</VolumeIDEnd>
<IssueIDStart>3</IssueIDStart>
<IssueIDEnd>3</IssueIDEnd>
</ArticleContext>
</ArticleInfo>
<ArticleHeader>
<AuthorGroup>
<Author AffiliationIDS="Aff1">
<AuthorName DisplayOrder="Western">
<GivenName>G.</GivenName>
<FamilyName>Lassmann</FamilyName>
</AuthorName>
</Author>
<Affiliation ID="Aff1">
<OrgName>Neurologischen Institut der Universität Wien</OrgName>
<OrgAddress>
<City>Wien</City>
</OrgAddress>
</Affiliation>
</AuthorGroup>
<Abstract ID="Abs1" Language="De">
<Heading>Zusammenfassung</Heading>
<Para>Es wird über die histochemisch nachweisbare Cholinesteraseaktivität der nervösen Formationen im Rahmen einer mit Neurombildung einhergehenden neurogenen Appendicopathie berichtet. Dabei war die zur Neurombildung führende primäre Hyperplasie der nervösen Formationen in den einzelnen Abschnitten des Organes zu beobachten. Eine Cholinesteraseaktivität des zentralen Neuromknotens war wie zu erwarten nachweisbar. Es handelt sich um einen Befund, dem auch für gleichartige Neubildungen an anderen Orten des Magen-Darm-Traktes grundsätzliche Bedeutung zukommt.</Para>
<Para>Die histochemische Darstellung erfolgte mit der von<Emphasis Type="SmallCaps">Gerebtzoff</Emphasis> angegebenen Modifikation der Methode von<Emphasis Type="SmallCaps">Koelle</Emphasis> u.<Emphasis Type="SmallCaps">Friedenwald</Emphasis>. Die Spezifität der Acetylcholinesterase wurde durch entsprechende Kontrolluntersuchungen verifiziert.</Para>
</Abstract>
<ArticleNote Type="Misc">
<SimplePara>Mit 1 Textabbildung</SimplePara>
</ArticleNote>
</ArticleHeader>
<BodyRef FileRef="BodyRef/PDF/401_2004_Article_BF00687194.pdf" TargetType="PDF"/>
<ArticleBackmatter>
<Bibliography ID="Bib1">
<Heading>Literatur</Heading>
<Citation ID="CR1">
<BibBook>
<BibAuthorName>
<Initials>F.</Initials>
<FamilyName>Feyrter</FamilyName>
</BibAuthorName>
<Year>1951</Year>
<BookTitle>Über die Pathologie der vegetativ nervösen Peripherie und ihrer ganglionären Regulationsstätten</BookTitle>
<PublisherName>W. Maudrich</PublisherName>
<PublisherLocation>Wien</PublisherLocation>
</BibBook>
<BibUnstructured>
<Emphasis Type="SmallCaps">Feyrter, F.</Emphasis>: Über die Pathologie der vegetativ nervösen Peripherie und ihrer ganglionären Regulationsstätten. Wien: W. Maudrich 1951.</BibUnstructured>
</Citation>
<Citation ID="CR2">
<BibUnstructured>
<Emphasis Type="SmallCaps">Lassmann, G.</Emphasis>: Die Darstellung der spezifischen Cholinesterase in den nervösen Formationen der menschlichen Appendix. (Im Druck.)</BibUnstructured>
</Citation>
<Citation ID="CR3">
<BibUnstructured>
<Emphasis Type="SmallCaps">Riopelle, J. L.</Emphasis>: Sur les proliferations nerveuses de la vesicule biliaire (neuromatoses vesiculaires). Le Journal de l'Hotel-Dieu de Montreal.</BibUnstructured>
</Citation>
<Citation ID="CR4">
<BibArticle>
<BibAuthorName>
<Initials>Ph.</Initials>
<FamilyName>Stöhr</FamilyName>
<Suffix>Jr.</Suffix>
</BibAuthorName>
<Year>1930</Year>
<ArticleTitle Language="De">Mikroskopische Studien zur Innervation des Magen-Darm-Kanales</ArticleTitle>
<JournalTitle>Z. Zellforsch.</JournalTitle>
<VolumeID>12</VolumeID>
<FirstPage>66</FirstPage>
</BibArticle>
<BibUnstructured>
<Emphasis Type="SmallCaps">Stöhr, Ph.</Emphasis>, Jr.: Mikroskopische Studien zur Innervation des Magen-Darm-Kanales. Z. Zellforsch.,<Emphasis Type="Bold">12</Emphasis>, 66 (1930);<Emphasis Type="Bold">16</Emphasis>, 123 (1932);<Emphasis Type="Bold">21</Emphasis>, 143 (1934);<Emphasis Type="Bold">27</Emphasis>, 341 (1937);<Emphasis Type="Bold">34</Emphasis>, 1 (1948).</BibUnstructured>
</Citation>
</Bibliography>
</ArticleBackmatter>
</Article>
</Issue>
</Volume>
</Journal>
</Publisher>